<?xml version="1.0" ?>
<PyBrain>
	<Network class="pybrain.structure.networks.feedforward.FeedForwardNetwork" name="FeedForwardNetwork-83">
		<name val="'FeedForwardNetwork-83'"/>
		<Modules>
			<LinearLayer class="pybrain.structure.modules.linearlayer.LinearLayer" inmodule="True" name="in">
				<dim val="4"/>
				<name val="'in'"/>
			</LinearLayer>
			<LinearLayer class="pybrain.structure.modules.linearlayer.LinearLayer" name="out" outmodule="True">
				<dim val="3"/>
				<name val="'out'"/>
			</LinearLayer>
			<BiasUnit class="pybrain.structure.modules.biasunit.BiasUnit" name="bias">
				<name val="'bias'"/>
			</BiasUnit>
			<SigmoidLayer class="pybrain.structure.modules.sigmoidlayer.SigmoidLayer" name="hidden0">
				<dim val="15"/>
				<name val="'hidden0'"/>
			</SigmoidLayer>
			<SigmoidLayer class="pybrain.structure.modules.sigmoidlayer.SigmoidLayer" name="hidden1">
				<dim val="15"/>
				<name val="'hidden1'"/>
			</SigmoidLayer>
		</Modules>
		<Connections>
			<FullConnection class="pybrain.structure.connections.full.FullConnection" name="FullConnection-77">
				<inmod val="bias"/>
				<outmod val="out"/>
				<Parameters>[-0.18958600874626277, 1.6923670198310075, -0.21126346192451459]</Parameters>
			</FullConnection>
			<FullConnection class="pybrain.structure.connections.full.FullConnection" name="FullConnection-78">
				<inmod val="bias"/>
				<outmod val="hidden0"/>
				<Parameters>[0.10657225480912878, -1.2050427696323442, 1.2106217744669259, -1.2129640923215868, 0.98530111592924141, 1.600054863489486, 0.18241360590915134, 1.7339764623120115, 1.0429908321377666, -0.7235128527799749, -0.3192417349911798, -1.0283253002054553, 0.51715658529437247, -2.1905282602524605, 0.50076159405170184]</Parameters>
			</FullConnection>
			<FullConnection class="pybrain.structure.connections.full.FullConnection" name="FullConnection-79">
				<inmod val="bias"/>
				<outmod val="hidden1"/>
				<Parameters>[1.2056035923996178, -0.30242146594096381, -0.13551903867894893, -0.71880315366668512, 0.61148194028640468, -1.3290281415497729, -1.1704731989564756, 1.3303475403419625, -0.20962051367794513, 1.1741592070144073, -0.22186417622103136, -1.0463052445058889, -0.50450498799723076, 0.28017827931041123, -2.1129796149674878]</Parameters>
			</FullConnection>
			<FullConnection class="pybrain.structure.connections.full.FullConnection" name="FullConnection-82">
				<inmod val="in"/>
				<outmod val="hidden0"/>
				<Parameters>[-1.2423873135072407, -0.49993936608779393, 0.44517120208702216, -1.1129970272474112, -0.30491608174995516, 2.0151473742423756, 1.1555436660469323, -1.1073381177636894, 0.10528743277789525, 0.17462883537000071, -2.9718374349962025, 0.4108835816310808, -0.87787383674847574, -1.297543476228546, 3.0197988899338255, 0.69225703466949484, 1.744671287336631, -1.7772581777566321, -2.5420459649753533, 1.1682382050578921, 0.25238182009825877, -0.60587322920017472, -2.5954414355303226, 0.64596143729491284, 0.2908929865513063, -0.42024572188457954, -1.4322376922043278, -1.5494231981245679, 0.47675320952333566, -1.0769033544306179, -1.3398488988112764, -0.43784267560839452, 0.21621054963866806, 0.46580877839992058, -2.5551231126129466, 0.11009457036524151, -0.89163941693172177, 1.3155704737689007, 0.036033095080336051, 0.44471386627712528, -0.79869977772010381, 1.0466097516626083, -1.8585429680870331, -0.27029843149823451, -1.0342408073086824, -0.50872284127530887, -0.072740046888641552, 1.6642657556458544, -0.0035419965496897069, 0.75285169047018152, 1.3256874510101202, -0.0061547851702501754, -0.11255623877478782, 2.765265359438267, 1.0050616566954709, -1.3469438856811102, 1.2288560943478779, 0.92618023430903318, 0.19309410444993585, -0.052121074782477302]</Parameters>
			</FullConnection>
			<FullConnection class="pybrain.structure.connections.full.FullConnection" name="FullConnection-80">
				<inmod val="hidden0"/>
				<outmod val="hidden1"/>
				<Parameters>[1.2769360961452121, -0.46554186082825771, 1.0602003193258906, -0.99490651157804177, 1.7824484458854599, 0.56742490378730159, -1.7247482028537959, -0.70496274327066122, 1.3211198009196758, -1.0358337976265859, -1.0434036961646642, 0.29229466788535824, 1.3556878104631824, -0.31837120128499591, 0.92851479155395567, 0.042233510409966687, 1.2053081876503107, -0.98376484575536871, 0.43859456528674273, 0.36566396547731089, -1.1865932369670948, -0.45700703850840663, 1.3220652480748527, -0.28995525621004847, 1.4687818005435758, 0.22461017794826399, 0.052099903201727443, -2.1372376611140562, 1.757976877089128, -1.4195962032081086, -0.25755696711147075, -0.035562628816992591, -0.24591389294693783, 0.52637117003908018, 0.1453584106016976, -0.66042029685793846, -0.64907687019814042, -0.86403874049341389, -0.061012418002047535, -0.207796003182325, -1.1328976475886363, -1.5522411918349419, 1.0914303103218754, -0.89183086906093656, -0.19693690286053811, -0.26604905733230161, -1.1382941094958039, -0.66162378760044926, 1.0962559780047341, -2.7098948279784079, 0.29187597365461138, 1.1841757405488156, -1.7602098127512962, 0.54867245634813055, 0.93065954710086285, 0.57135536677443888, 1.6618105628887052, 0.14875336372578576, -1.000942389764909, -0.15968593047833746, -0.28742111418269362, -1.0544293467921024, -0.67457201239501452, 1.1076408724040259, -0.48256250640890497, 0.37364056997359602, -0.099023542695200042, -1.9427589944559105, 1.0167161788547407, -0.75157164822221556, 2.1457063948199937, -1.6244430756587467, -0.10700783274870927, -0.50367145207331543, -0.10187468667069016, -0.87998260020387431, -0.27697551529357872, -0.23316918687449198, -0.5851215697005101, 0.9395475316075198, -1.0256602102563763, -0.37935405726566734, 0.016598122828141861, -0.17257950389192026, 0.51226290300024935, 1.396814181342364, -0.1077480910475304, -0.19374785842822309, 0.60723215460034963, -0.55992548471133508, -1.2118062525822666, 2.8391582193185916, -3.0351280105401295, 1.1760493246736048, -3.7862069412161641, -1.9432223830619459, 0.45653812067776151, -1.9994185727906706, -1.6972065196915977, 0.62639457971523627, -0.24141814756127794, 0.6315902934276878, 0.49676985509403115, 1.8886755025311641, 1.1115959881025725, 0.45169710827457488, -0.6049630553049804, 0.66613926424059178, 1.3537104897896914, -0.98536309238928632, 0.23098612831767135, -0.48798640413098104, 0.48619559904366744, 0.087525457544724503, -2.9473643025239058, 0.15546663248316941, 0.19998452587485913, -0.58263969292306639, 0.15407328395037703, 1.8965621997142357, 1.1185578198066639, 0.62299376443734689, 0.082856343666037793, 0.058954768954895702, -0.89611125997276764, 1.499044324644752, -1.709144004959863, 0.54652150327735149, -0.55660907373142665, 0.44688353661139502, -0.17388908114025045, -0.21642459510633419, -1.5895571524387693, 0.40221948701174065, -1.4478294445174915, -0.75736479674289758, 0.34331390229569231, -0.36185746608570662, -1.904743592991978, 0.50177567645328802, 0.4397769025341422, 1.8655683331879782, 0.094871924326399071, 0.010769550215406064, -1.3591635503012571, 2.0633874234310801, -1.7208906883642339, 0.10396424600552628, 0.8613543066141881, 0.29321019446921837, -1.3076543253757891, -0.74302595841552532, -0.99123200861533678, 0.84272630916291147, -0.40953326181570138, -0.12949946132786547, -0.65929849368443305, -0.78667447401547752, 0.67872574422404675, 1.9213516254233531, -2.1063707099576425, -0.01430618029013859, -1.5633453553476462, 0.60327069091869578, -0.52051138749324422, 1.2789324781232196, 1.827912468804517, 0.37897855398771657, 0.020086812741554074, -1.4948465807589542, -2.8356181873409749, 0.49542181669460045, -2.2541859012598215, -0.54515371556621894, 1.1662665683935804, -1.4853392655742397, -0.57926138404681138, -0.46345848496901321, 1.8666335098451634, 0.07451315900455685, 0.29960859498151265, -1.1408216764700823, 2.3281966953155795, -1.0753979979685118, -0.28135720991492763, 1.2120159414704768, -1.7381182457742164, 0.17820991991001722, 0.56364369734913544, 0.57756907647488553, 0.63003081571221986, 0.32261366783775486, 0.03105347277648839, 2.7410518968286697, 1.1447723605943911, 0.14807041048828454, -1.9411523544747014, 0.93853576564132257, 0.29747004816110545, 0.73132237556055768, -0.20534477634766191, -0.32054289277756959, -0.67728296175029346, -2.9568238173661094, 0.41621153250935333, -0.45552063655864117, 1.6815716940438639, 1.3801510510375128, -0.55141421203565411, -0.37462210506134608, -1.4336902367947688, -0.3651991439307018, 0.31418023653669225, 0.93981737276884936, 0.99845922528234965, -0.40806520194572599, -0.78263121999634078, -0.51174898683699399, 0.31355734037351746, -0.087002440312615587, -0.77271156902586113, 0.3544890948238229, 0.2131786988842343, 1.5810460656439607, -1.309382799088977]</Parameters>
			</FullConnection>
			<FullConnection class="pybrain.structure.connections.full.FullConnection" name="FullConnection-81">
				<inmod val="hidden1"/>
				<outmod val="out"/>
				<Parameters>[0.015298147055055434, -0.66475269418073857, 0.0052054338618802223, -0.57742507856030756, 0.16581957560102623, -0.46424037796483864, -2.2873434335759595, 1.0667886155028099, -0.071291520745528095, -0.76844924181173868, -0.50369131047479199, -0.57399178287948471, -0.32240052600383484, 1.568192573842824, 0.053046617749657146, 0.47781804306425629, -1.2015063342238976, 0.75005802194390925, -0.49711480250389584, -0.97082223498365638, 0.17745768435043521, -1.8848180040583207, -1.5236689787236468, 1.1975910976019022, -0.77162095254184182, 0.52761471697175322, -1.018610836666197, -0.14114859970070961, 0.44849967915532502, 0.08104513281718706, 1.2125733245380219, 1.1088746021039078, -0.36548886717007595, 0.01443324700386441, 0.081060200892579148, 0.045945450404560564, -2.2582838505181826, 1.7808417214837022, -1.040974852463219, -1.0957868651826144, 0.24693695271695346, -1.8583380492512864, -1.4246361546777324, -0.35006608465933231, 1.0991205866274656]</Parameters>
			</FullConnection>
		</Connections>
	</Network>
</PyBrain>
